[
   {
    "_id": "67rdca3eeb7f6f324geed471815",
    "absent": false,
    "brands": "Foxxx Irons",
    "category": "machines",
    "favorite": false,
    "hit": true,
    "likeStatus": true,
    "name": "Foxxx Kitsune Mini Black Vintage RCA",
    "novelty": false,
    "popular": false,
    "price": 6000,
    "promotion": false,
    "sales": 0,
    "url": "../../assets/productsCards/machines/foxx-kitsune.png",
    "userId": "hzgza7DgEvedSdSa2BsH7yd7Hw93"
  },
 {
    "_id": "67rdca3eeb7f6fgeed455656771824",
    "absent": false,
    "brands": " R.T.E.",
    "category": "machines",
    "favorite": false,
    "hit": true,
    "likeStatus": true,
    "name": "V-machine Shader",
    "novelty": false,
    "popular": false,
    "price": 7800,
    "promotion": false,
    "sales": 0,
    "url": "../../assets/productsCards/machines/V-machine-Shader.jpg",
    "userId": "hzgza7DgEvedSdSa2BsH7yd7Hw93"
  },
 {
    "_id": "67rdca3eeb7f6fgeed455656771825",
    "absent": false,
    "brands": " R.T.E.",
    "category": "machines",
    "favorite": false,
    "hit": true,
    "likeStatus": true,
    "name": "Tattoomechanics-W-Liner",
    "novelty": false,
    "popular": false,
    "price": 12300,
    "promotion": false,
    "sales": 0,
    "url": "../../assets/productsCards/machines/Tattoomechanics-W-Liner.jpg",
    "userId": "hzgza7DgEvedSdSa2BsH7yd7Hw93"
  },
{
    "_id": "67rdca3eeb7f6fgeed455656771964",
    "absent": false,
    "brands": "Verge",
    "category": "paints",
    "favorite": false,
    "hit": false,
    "likeStatus": true,
    "name": "SULUAPE Black - Intenze",
    "novelty": false,
    "popular": false,
    "price": 890,
    "promotion": false,
    "sales": 0,
    "url": "../../assets/productsCards/paints/SULUAPE Black - Intenze.jpg",
    "userId": "JMVUr8hTrKZQNriQIIJoXcdbpGi2"
  },
 {
    "_id": "67rdca3eeb7f6fgeed455656771965",
    "absent": false,
    "brands": " R.T.E.",
    "category": "paints",
    "favorite": false,
    "hit": false,
    "likeStatus": true,
    "name": "Sumi Black Intenze - Noir",
    "novelty": false,
    "popular": false,
    "price": 1500,
    "promotion": false,
    "sales": 0,
    "url": "../../assets/productsCards/paints/Sumi Black Intenze.jpg",
    "userId": "JMVUr8hTrKZQNriQIIJoXcdbpGi2"
  },
 {
    "_id": "67rdca3eeb7f6fgeed455656771966",
    "absent": false,
    "brands": "Mustang Tattoo",
    "category": "paints",
    "favorite": false,
    "hit": false,
    "likeStatus": true,
    "name": "Super Black - Nocturnal Tattoo",
    "novelty": false,
    "popular": false,
    "price": 570,
    "promotion": false,
    "sales": 0,
    "url": "../../assets/productsCards/paints/Super Black - Nocturnal Tattoo.jpg",
    "userId": "JMVUr8hTrKZQNriQIIJoXcdbpGi2"
  },
 {
    "_id": "67rdca3eeb7f6fgeed455656771967",
    "absent": false,
    "brands": "Мастерская точной механики",
    "category": "paints",
    "favorite": false,
    "hit": false,
    "likeStatus": true,
    "name": "The Mixer - Separator",
    "novelty": false,
    "popular": false,
    "price": 770,
    "promotion": false,
    "sales": 0,
    "url": "../../assets/productsCards/paints/The Mixer - Separator.png",
    "userId": "JMVUr8hTrKZQNriQIIJoXcdbpGi2"
  },
   {
    "_id": "67rdca3eeb7f6fgeed455656772265",
    "absent": false,
    "brands": "Мастерская точной механики",
    "category": "tips",
    "favorite": false,
    "hit": false,
    "likeStatus": true,
    "name": "Наконечник - Verge Round 15",
    "novelty": false,
    "popular": false,
    "price": 1950,
    "promotion": false,
    "sales": 0,
    "url": "../../assets/productsCards/tips/Verge Round 15.jpg",
    "userId": "hzgza7DgEvedSdSa2BsH7yd7Hw93"
  }

]